<?xml version="1.0" encoding="UTF-8"?>
<objects serializationModel="Studio.02.02.00">
	<object class="AudioFile" id="{4819be41-6aa9-45eb-be0c-a8b23155863e}">
		<property name="assetPath">
			<value>GuitarHit (4).wav</value>
		</property>
		<property name="frequencyInKHz">
			<value>44.0999985</value>
		</property>
		<property name="channelCount">
			<value>2</value>
		</property>
		<property name="length">
			<value>0.34414965986394558</value>
		</property>
		<relationship name="masterAssetFolder">
			<destination>{19071a00-b218-4d0a-880e-ebfbf0b0ee72}</destination>
		</relationship>
	</object>
</objects>
